[
  {
    "title": "总裁来袭：豪门联姻",
    "pic": "http://localhost:3000/pc/assets/images/hot1.jpg",
    "price": "5阅币⁄千字"
  },
  {
    "title": "总裁来袭：豪门联姻",
    "pic": "http://localhost:3000/pc/assets/images/hot1.jpg",
    "price": "5阅币⁄千字"
  },
  {
    "title": "总裁来袭：豪门联姻",
    "pic": "http://localhost:3000/pc/assets/images/hot1.jpg",
    "price": "5阅币⁄千字"
  },
  {
    "title": "总裁来袭：豪门联姻",
    "pic": "http://localhost:3000/pc/assets/images/hot1.jpg",
    "price": "5阅币⁄千字"
  },
  {
    "title": "总裁来袭：豪门联姻",
    "pic": "http://localhost:3000/pc/assets/images/hot1.jpg",
    "price": "5阅币⁄千字"
  }
]